MoYeRanSoft/__init__.py
MoYeRanSoft-0.0.0.dist-info/METADATA
MoYeRanSoft-0.0.0.dist-info/WHEEL
MoYeRanSoft-0.0.0.dist-info/top_level.txt
MoYeRanSoft-0.0.0.dist-info/RECORD
