Metadata-Version: 2.1
Name: MoYeRanSoft
Version: 0.0.0
Summary: This is a module for MoYeRanSoft.
Home-page: https://github.com/MoYeRanQianZhi
Author: MoYeRanQianZhi
Author-email: moyeranqianzhi@gmail.com
License: MIT License
Classifier: Development Status :: 3 - Alpha
Classifier: Intended Audience :: Developers
Classifier: License :: OSI Approved :: MIT License
Classifier: Programming Language :: Python
Classifier: Programming Language :: Python :: 3
Classifier: Programming Language :: Python :: 3.6
Classifier: Programming Language :: Python :: 3.7
Classifier: Programming Language :: Python :: 3.8
Classifier: Programming Language :: Python :: 3.9
Requires-Python: >=3.6.0
